Metadata-Version: 1.1
Name: Socialsearch
Version: 0.1.2
Summary: A very Special Searcher
Home-page: UNKNOWN
Author: Borys Kostka
Author-email: borys.kostka09@gmail.com
License: MIT
Keywords: Searcher
Platform: UNKNOWN
Classifier: Development Status :: 5 - Production/Stable
Classifier: Intended Audience :: Education
Classifier: Operating System :: Microsoft :: Windows :: Windows 10
Classifier: License :: OSI Approved :: MIT License
Classifier: Programming Language :: Python :: 2
